cli_nb2py/__init__.py
cli_nb2py/main.py
cli_nb2py-0.7.5.dist-info/LICENSE
cli_nb2py-0.7.5.dist-info/METADATA
cli_nb2py-0.7.5.dist-info/WHEEL
cli_nb2py-0.7.5.dist-info/entry_points.txt
cli_nb2py-0.7.5.dist-info/top_level.txt
cli_nb2py-0.7.5.dist-info/RECORD
