Metadata-Version: 2.1
Name: cli-nb2py
Version: 0.7.5
Summary: Reliable Notebook to Python converter
Home-page: https://github.com/BardiaKh/nb2py
Author: Bardia Khosravi
Author-email: bardiakhosravi95@gmail.com
Classifier: Programming Language :: Python :: 3
Classifier: License :: OSI Approved :: MIT License
Classifier: Operating System :: OS Independent
Requires-Python: >=3.6
License-File: LICENSE
Requires-Dist: argparse
